{
  "annotations": {
    "list": [
      {
        "builtIn": 1,
        "datasource": {
          "type": "grafana",
          "uid": "-- Grafana --"
        },
        "enable": true,
        "hide": true,
        "iconColor": "rgba(0, 211, 255, 1)",
        "name": "Annotations & Alerts",
        "type": "dashboard"
      }
    ]
  },
  "editable": false,
  "fiscalYearStartMonth": 0,
  "graphTooltip": 1,
  "links": [
    {
      "asDropdown": false,
      "icon": "external link",
      "includeVars": false,
      "keepTime": false,
      "tags": [
        "home"
      ],
      "targetBlank": false,
      "title": "Home",
      "tooltip": "",
      "type": "dashboards",
      "url": ""
    },
    {
      "asDropdown": true,
      "icon": "external link",
      "includeVars": false,
      "keepTime": false,
      "tags": [
        "dashboard"
      ],
      "targetBlank": false,
      "title": "TrinityX Dashboards",
      "tooltip": "",
      "type": "dashboards",
      "url": ""
    }
  ],
  "liveNow": false,
  "panels": [
    {
      "collapsed": false,
      "gridPos": {
        "h": 1,
        "w": 24,
        "x": 0,
        "y": 0
      },
      "id": 28,
      "panels": [],
      "title": "Cluster Statistics",
      "type": "row"
    },
    {
      "datasource": {
        "type": "prometheus",
        "uid": "trixprometheus"
      },
      "description": "",
      "fieldConfig": {
        "defaults": {
          "color": {
            "mode": "palette-classic"
          },
          "custom": {
            "hideFrom": {
              "legend": false,
              "tooltip": false,
              "viz": false
            }
          },
          "mappings": []
        },
        "overrides": [
          {
            "matcher": {
              "id": "byName",
              "options": "idle"
            },
            "properties": [
              {
                "id": "color",
                "value": {
                  "fixedColor": "#70707080",
                  "mode": "fixed"
                }
              }
            ]
          },
          {
            "matcher": {
              "id": "byName",
              "options": "slurm_user_other"
            },
            "properties": [
              {
                "id": "color",
                "value": {
                  "fixedColor": "#73bf6980",
                  "mode": "fixed"
                }
              }
            ]
          },
          {
            "matcher": {
              "id": "byName",
              "options": "slurm_system_other"
            },
            "properties": [
              {
                "id": "color",
                "value": {
                  "fixedColor": "#fade2a80",
                  "mode": "fixed"
                }
              }
            ]
          },
          {
            "matcher": {
              "id": "byName",
              "options": "slurm_user_job"
            },
            "properties": [
              {
                "id": "color",
                "value": {
                  "fixedColor": "dark-green",
                  "mode": "fixed"
                }
              }
            ]
          },
          {
            "matcher": {
              "id": "byName",
              "options": "slurm_system_job"
            },
            "properties": [
              {
                "id": "color",
                "value": {
                  "fixedColor": "dark-yellow",
                  "mode": "fixed"
                }
              }
            ]
          },
          {
            "matcher": {
              "id": "byName",
              "options": "management"
            },
            "properties": [
              {
                "id": "color",
                "value": {
                  "fixedColor": "#3274d980",
                  "mode": "fixed"
                }
              }
            ]
          }
        ]
      },
      "gridPos": {
        "h": 8,
        "w": 3,
        "x": 0,
        "y": 1
      },
      "id": 39,
      "options": {
        "legend": {
          "displayMode": "list",
          "placement": "bottom",
          "showLegend": false
        },
        "pieType": "pie",
        "reduceOptions": {
          "calcs": [
            "mean"
          ],
          "fields": "",
          "values": false
        },
        "tooltip": {
          "mode": "single",
          "sort": "none"
        }
      },
      "targets": [
        {
          "datasource": {
            "type": "prometheus",
            "uid": "trixprometheus"
          },
          "editorMode": "code",
          "expr": "sum(rate(slurm_job_user_cpu_time{jobid=~\"$job_id\",hostname=~\"$hostname\"}[$__rate_interval:]))",
          "hide": false,
          "instant": false,
          "interval": "",
          "legendFormat": "slurm_user_job",
          "range": true,
          "refId": "B"
        },
        {
          "datasource": {
            "type": "prometheus",
            "uid": "trixprometheus"
          },
          "editorMode": "code",
          "expr": "sum(rate(slurm_job_user_cpu_time{jobid!~\"$job_id\",hostname=~\"$hostname\"}[$__rate_interval:]))",
          "hide": false,
          "instant": false,
          "interval": "",
          "legendFormat": "slurm_user_other",
          "range": true,
          "refId": "D"
        },
        {
          "datasource": {
            "type": "prometheus",
            "uid": "trixprometheus"
          },
          "editorMode": "code",
          "expr": "sum(rate(slurm_job_system_cpu_time{jobid=~\"$job_id\",hostname=~\"$hostname\"}[$__rate_interval:]))",
          "hide": false,
          "instant": false,
          "interval": "",
          "legendFormat": "slurm_system_job",
          "range": true,
          "refId": "E"
        },
        {
          "datasource": {
            "type": "prometheus",
            "uid": "trixprometheus"
          },
          "editorMode": "code",
          "expr": "sum(rate(slurm_job_system_cpu_time{jobid!~\"$job_id\",hostname=~\"$hostname\"}[$__rate_interval:]))",
          "hide": false,
          "instant": false,
          "interval": "",
          "legendFormat": "slurm_system_other",
          "range": true,
          "refId": "F"
        },
        {
          "datasource": {
            "type": "prometheus",
            "uid": "trixprometheus"
          },
          "editorMode": "code",
          "expr": "sum(rate(node_cpu_seconds_total{mode=\"idle\",hostname=~\"$hostname\"}[$__rate_interval:]))",
          "hide": false,
          "instant": false,
          "interval": "",
          "legendFormat": "idle",
          "range": true,
          "refId": "A"
        },
        {
          "datasource": {
            "type": "prometheus",
            "uid": "trixprometheus"
          },
          "editorMode": "code",
          "expr": "sum(rate(node_cpu_seconds_total{hostname=~\"$hostname\"}[$__rate_interval:]))",
          "hide": false,
          "instant": false,
          "legendFormat": "max_load",
          "range": true,
          "refId": "C"
        },
        {
          "datasource": {
            "type": "prometheus",
            "uid": "trixprometheus"
          },
          "editorMode": "code",
          "expr": "sum(rate(node_cpu_seconds_total{hostname=~\"$hostname\"}[$__rate_interval:]))\r\n- sum(rate(node_cpu_seconds_total{mode=\"idle\",hostname=~\"$hostname\"}[$__rate_interval:]))\r\n- (sum(rate(slurm_job_total_cpu_time{hostname=~\"$hostname\"}[$__rate_interval:]))  or vector(0) )\r\n",
          "hide": false,
          "instant": false,
          "interval": "",
          "legendFormat": "management",
          "range": true,
          "refId": "G"
        }
      ],
      "title": "CPU Usage Breakdown",
      "transformations": [
        {
          "id": "configFromData",
          "options": {
            "applyTo": {
              "id": "byType",
              "options": "number"
            },
            "configRefId": "C",
            "mappings": [
              {
                "fieldName": "max_load",
                "handlerKey": "max",
                "reducerId": "max"
              }
            ]
          }
        }
      ],
      "transparent": true,
      "type": "piechart"
    },
    {
      "datasource": {
        "type": "prometheus",
        "uid": "trixprometheus"
      },
      "description": "",
      "fieldConfig": {
        "defaults": {
          "color": {
            "mode": "palette-classic"
          },
          "custom": {
            "axisCenteredZero": false,
            "axisColorMode": "text",
            "axisLabel": "",
            "axisPlacement": "auto",
            "axisSoftMin": 0,
            "barAlignment": 0,
            "drawStyle": "line",
            "fillOpacity": 10,
            "gradientMode": "none",
            "hideFrom": {
              "legend": false,
              "tooltip": false,
              "viz": false
            },
            "insertNulls": false,
            "lineInterpolation": "linear",
            "lineStyle": {
              "fill": "solid"
            },
            "lineWidth": 1,
            "pointSize": 2,
            "scaleDistribution": {
              "type": "linear"
            },
            "showPoints": "never",
            "spanNulls": false,
            "stacking": {
              "group": "A",
              "mode": "normal"
            },
            "thresholdsStyle": {
              "mode": "off"
            }
          },
          "mappings": [],
          "thresholds": {
            "mode": "absolute",
            "steps": [
              {
                "color": "green",
                "value": null
              },
              {
                "color": "red",
                "value": 80
              }
            ]
          }
        },
        "overrides": [
          {
            "matcher": {
              "id": "byName",
              "options": "idle"
            },
            "properties": [
              {
                "id": "color",
                "value": {
                  "fixedColor": "#70707080",
                  "mode": "fixed"
                }
              }
            ]
          },
          {
            "matcher": {
              "id": "byName",
              "options": "slurm_user_other"
            },
            "properties": [
              {
                "id": "color",
                "value": {
                  "fixedColor": "#73bf6980",
                  "mode": "fixed"
                }
              }
            ]
          },
          {
            "matcher": {
              "id": "byName",
              "options": "slurm_system_other"
            },
            "properties": [
              {
                "id": "color",
                "value": {
                  "fixedColor": "#fade2a80",
                  "mode": "fixed"
                }
              }
            ]
          },
          {
            "matcher": {
              "id": "byName",
              "options": "slurm_user_job"
            },
            "properties": [
              {
                "id": "color",
                "value": {
                  "fixedColor": "dark-green",
                  "mode": "fixed"
                }
              },
              {
                "id": "custom.fillOpacity",
                "value": 70
              }
            ]
          },
          {
            "matcher": {
              "id": "byName",
              "options": "slurm_system_job"
            },
            "properties": [
              {
                "id": "color",
                "value": {
                  "fixedColor": "dark-yellow",
                  "mode": "fixed"
                }
              },
              {
                "id": "custom.fillOpacity",
                "value": 70
              }
            ]
          },
          {
            "matcher": {
              "id": "byName",
              "options": "management"
            },
            "properties": [
              {
                "id": "color",
                "value": {
                  "fixedColor": "#3274d980",
                  "mode": "fixed"
                }
              }
            ]
          }
        ]
      },
      "gridPos": {
        "h": 8,
        "w": 21,
        "x": 3,
        "y": 1
      },
      "id": 10,
      "options": {
        "legend": {
          "calcs": [
            "mean"
          ],
          "displayMode": "list",
          "placement": "bottom",
          "showLegend": true
        },
        "tooltip": {
          "mode": "multi",
          "sort": "none"
        }
      },
      "targets": [
        {
          "datasource": {
            "type": "prometheus",
            "uid": "trixprometheus"
          },
          "editorMode": "code",
          "expr": "sum(rate(slurm_job_user_cpu_time{jobid=~\"$job_id\",hostname=~\"$hostname\"}[$__rate_interval:]))",
          "hide": false,
          "instant": false,
          "interval": "",
          "legendFormat": "slurm_user_job",
          "range": true,
          "refId": "B"
        },
        {
          "datasource": {
            "type": "prometheus",
            "uid": "trixprometheus"
          },
          "editorMode": "code",
          "expr": "sum(rate(slurm_job_user_cpu_time{jobid!~\"$job_id\",hostname=~\"$hostname\"}[$__rate_interval:]))",
          "hide": false,
          "instant": false,
          "interval": "",
          "legendFormat": "slurm_user_other",
          "range": true,
          "refId": "D"
        },
        {
          "datasource": {
            "type": "prometheus",
            "uid": "trixprometheus"
          },
          "editorMode": "code",
          "expr": "sum(rate(slurm_job_system_cpu_time{jobid=~\"$job_id\",hostname=~\"$hostname\"}[$__rate_interval:]))",
          "hide": false,
          "instant": false,
          "interval": "",
          "legendFormat": "slurm_system_job",
          "range": true,
          "refId": "E"
        },
        {
          "datasource": {
            "type": "prometheus",
            "uid": "trixprometheus"
          },
          "editorMode": "code",
          "expr": "sum(rate(slurm_job_system_cpu_time{jobid!~\"$job_id\",hostname=~\"$hostname\"}[$__rate_interval:]))",
          "hide": false,
          "instant": false,
          "interval": "",
          "legendFormat": "slurm_system_other",
          "range": true,
          "refId": "F"
        },
        {
          "datasource": {
            "type": "prometheus",
            "uid": "trixprometheus"
          },
          "editorMode": "code",
          "expr": "sum(rate(node_cpu_seconds_total{mode=\"idle\",hostname=~\"$hostname\"}[$__rate_interval:]))",
          "hide": false,
          "instant": false,
          "interval": "",
          "legendFormat": "idle",
          "range": true,
          "refId": "A"
        },
        {
          "datasource": {
            "type": "prometheus",
            "uid": "trixprometheus"
          },
          "editorMode": "code",
          "expr": "sum(rate(node_cpu_seconds_total{hostname=~\"$hostname\"}[$__rate_interval:]))",
          "hide": false,
          "instant": false,
          "legendFormat": "max_load",
          "range": true,
          "refId": "C"
        },
        {
          "datasource": {
            "type": "prometheus",
            "uid": "trixprometheus"
          },
          "editorMode": "code",
          "expr": "sum(rate(node_cpu_seconds_total{hostname=~\"$hostname\"}[$__rate_interval:]))\r\n- sum(rate(node_cpu_seconds_total{mode=\"idle\",hostname=~\"$hostname\"}[$__rate_interval:]))\r\n- (sum(rate(slurm_job_total_cpu_time{hostname=~\"$hostname\"}[$__rate_interval:]))  or vector(0) )",
          "hide": false,
          "instant": false,
          "interval": "",
          "legendFormat": "management",
          "range": true,
          "refId": "G"
        }
      ],
      "title": "CPU Usage over time",
      "transformations": [
        {
          "id": "configFromData",
          "options": {
            "applyTo": {
              "id": "byType",
              "options": "number"
            },
            "configRefId": "C",
            "mappings": [
              {
                "fieldName": "max_load",
                "handlerKey": "max",
                "reducerId": "max"
              }
            ]
          }
        }
      ],
      "transparent": true,
      "type": "timeseries"
    },
    {
      "datasource": {
        "type": "prometheus",
        "uid": "trixprometheus"
      },
      "fieldConfig": {
        "defaults": {
          "color": {
            "mode": "fixed"
          },
          "mappings": [],
          "min": 0,
          "thresholds": {
            "mode": "absolute",
            "steps": [
              {
                "color": "green",
                "value": null
              }
            ]
          },
          "unit": "watt"
        },
        "overrides": []
      },
      "gridPos": {
        "h": 4,
        "w": 3,
        "x": 0,
        "y": 9
      },
      "id": 24,
      "options": {
        "colorMode": "value",
        "graphMode": "none",
        "justifyMode": "auto",
        "orientation": "auto",
        "reduceOptions": {
          "calcs": [
            "mean"
          ],
          "fields": "",
          "values": false
        },
        "textMode": "auto"
      },
      "pluginVersion": "10.1.2",
      "targets": [
        {
          "datasource": {
            "type": "prometheus",
            "uid": "trixprometheus"
          },
          "editorMode": "code",
          "expr": "sum(ipmi_dcmi_power_consumption_watts{hostname=~\"$hostname\"})",
          "hide": false,
          "instant": false,
          "legendFormat": "mean_consumption",
          "range": true,
          "refId": "B"
        }
      ],
      "title": "Mean Consumption",
      "transformations": [],
      "type": "stat"
    },
    {
      "datasource": {
        "type": "prometheus",
        "uid": "trixprometheus"
      },
      "fieldConfig": {
        "defaults": {
          "color": {
            "fixedColor": "#808080",
            "mode": "fixed"
          },
          "custom": {
            "axisCenteredZero": false,
            "axisColorMode": "text",
            "axisLabel": "",
            "axisPlacement": "auto",
            "barAlignment": 0,
            "drawStyle": "line",
            "fillOpacity": 10,
            "gradientMode": "none",
            "hideFrom": {
              "legend": false,
              "tooltip": false,
              "viz": false
            },
            "insertNulls": false,
            "lineInterpolation": "linear",
            "lineWidth": 1,
            "pointSize": 5,
            "scaleDistribution": {
              "type": "linear"
            },
            "showPoints": "auto",
            "spanNulls": false,
            "stacking": {
              "group": "A",
              "mode": "none"
            },
            "thresholdsStyle": {
              "mode": "off"
            }
          },
          "mappings": [],
          "min": 0,
          "thresholds": {
            "mode": "absolute",
            "steps": [
              {
                "color": "green",
                "value": null
              }
            ]
          },
          "unit": "watt"
        },
        "overrides": []
      },
      "gridPos": {
        "h": 4,
        "w": 21,
        "x": 3,
        "y": 9
      },
      "id": 35,
      "options": {
        "legend": {
          "calcs": [],
          "displayMode": "list",
          "placement": "bottom",
          "showLegend": false
        },
        "tooltip": {
          "mode": "single",
          "sort": "none"
        }
      },
      "pluginVersion": "10.1.2",
      "targets": [
        {
          "datasource": {
            "type": "prometheus",
            "uid": "trixprometheus"
          },
          "editorMode": "code",
          "expr": "sum(ipmi_dcmi_power_consumption_watts{hostname=~\"$hostname\"})",
          "hide": false,
          "instant": false,
          "legendFormat": "__auto",
          "range": true,
          "refId": "B"
        }
      ],
      "transformations": [],
      "transparent": true,
      "type": "timeseries"
    },
    {
      "datasource": {
        "type": "prometheus",
        "uid": "trixprometheus"
      },
      "description": "Mean Efficiency",
      "fieldConfig": {
        "defaults": {
          "color": {
            "mode": "continuous-RdYlGr"
          },
          "mappings": [],
          "max": 1,
          "min": 0,
          "thresholds": {
            "mode": "absolute",
            "steps": [
              {
                "color": "green",
                "value": null
              }
            ]
          },
          "unit": "percentunit"
        },
        "overrides": []
      },
      "gridPos": {
        "h": 4,
        "w": 3,
        "x": 0,
        "y": 13
      },
      "id": 20,
      "options": {
        "colorMode": "value",
        "graphMode": "none",
        "justifyMode": "auto",
        "orientation": "auto",
        "reduceOptions": {
          "calcs": [
            "mean"
          ],
          "fields": "",
          "values": false
        },
        "textMode": "auto"
      },
      "pluginVersion": "10.1.2",
      "targets": [
        {
          "datasource": {
            "type": "prometheus",
            "uid": "trixprometheus"
          },
          "editorMode": "code",
          "expr": "(\r\n\tsum(rate(slurm_job_total_cpu_time{hostname=~\"$hostname\"}[$__rate_interval:])) OR vector(0)\r\n\r\n)\r\n/\r\n(\r\n\tsum(rate(node_cpu_seconds_total{hostname=~\"$hostname\"}[$__rate_interval:]))\r\n)",
          "hide": false,
          "instant": false,
          "legendFormat": "mean_efficiency",
          "range": true,
          "refId": "B"
        }
      ],
      "title": "Mean Efficiency",
      "transformations": [],
      "type": "stat"
    },
    {
      "datasource": {
        "type": "prometheus",
        "uid": "trixprometheus"
      },
      "description": "Efficiency",
      "fieldConfig": {
        "defaults": {
          "color": {
            "mode": "continuous-RdYlGr",
            "seriesBy": "last"
          },
          "custom": {
            "axisCenteredZero": false,
            "axisColorMode": "text",
            "axisLabel": "",
            "axisPlacement": "auto",
            "barAlignment": 0,
            "drawStyle": "line",
            "fillOpacity": 10,
            "gradientMode": "scheme",
            "hideFrom": {
              "legend": false,
              "tooltip": false,
              "viz": false
            },
            "insertNulls": false,
            "lineInterpolation": "linear",
            "lineStyle": {
              "fill": "solid"
            },
            "lineWidth": 1,
            "pointSize": 5,
            "scaleDistribution": {
              "type": "linear"
            },
            "showPoints": "auto",
            "spanNulls": false,
            "stacking": {
              "group": "A",
              "mode": "none"
            },
            "thresholdsStyle": {
              "mode": "off"
            }
          },
          "mappings": [],
          "max": 1,
          "min": 0,
          "thresholds": {
            "mode": "absolute",
            "steps": [
              {
                "color": "green",
                "value": null
              }
            ]
          },
          "unit": "percentunit"
        },
        "overrides": []
      },
      "gridPos": {
        "h": 4,
        "w": 21,
        "x": 3,
        "y": 13
      },
      "id": 34,
      "options": {
        "legend": {
          "calcs": [],
          "displayMode": "list",
          "placement": "bottom",
          "showLegend": false
        },
        "tooltip": {
          "mode": "single",
          "sort": "none"
        }
      },
      "pluginVersion": "10.1.2",
      "targets": [
        {
          "datasource": {
            "type": "prometheus",
            "uid": "trixprometheus"
          },
          "editorMode": "code",
          "expr": "(\r\n\tsum(rate(slurm_job_total_cpu_time{hostname=~\"$hostname\"}[$__rate_interval:])) OR vector(0)\r\n)\r\n/\r\n(\r\n\tsum(rate(node_cpu_seconds_total{hostname=~\"$hostname\"}[$__rate_interval:]))\r\n)",
          "hide": false,
          "instant": false,
          "legendFormat": "efficiency",
          "range": true,
          "refId": "B"
        }
      ],
      "transformations": [],
      "transparent": true,
      "type": "timeseries"
    },
    {
      "collapsed": false,
      "gridPos": {
        "h": 1,
        "w": 24,
        "x": 0,
        "y": 17
      },
      "id": 29,
      "panels": [],
      "title": "Job Statistics",
      "type": "row"
    },
    {
      "datasource": {
        "type": "prometheus",
        "uid": "trixprometheus"
      },
      "fieldConfig": {
        "defaults": {
          "color": {
            "fixedColor": "#808080",
            "mode": "fixed"
          },
          "mappings": [],
          "min": 0,
          "thresholds": {
            "mode": "absolute",
            "steps": [
              {
                "color": "green",
                "value": null
              }
            ]
          },
          "unit": "watt"
        },
        "overrides": []
      },
      "gridPos": {
        "h": 4,
        "w": 3,
        "x": 0,
        "y": 18
      },
      "id": 42,
      "options": {
        "colorMode": "value",
        "graphMode": "none",
        "justifyMode": "auto",
        "orientation": "auto",
        "reduceOptions": {
          "calcs": [
            "mean"
          ],
          "fields": "",
          "values": false
        },
        "textMode": "auto"
      },
      "pluginVersion": "10.1.2",
      "targets": [
        {
          "datasource": {
            "type": "prometheus",
            "uid": "trixprometheus"
          },
          "editorMode": "code",
          "expr": "sum(ipmi_dcmi_power_consumption_watts{hostname=~\"$hostname\"})\r\n*\r\nsum(rate(slurm_job_total_cpu_time{jobid=~\"$job_id\",hostname=~\"$hostname\"}[$__rate_interval:]))\r\n/\r\nsum(rate(node_cpu_seconds_total{hostname=~\"$hostname\"}[$__rate_interval:]))",
          "hide": false,
          "instant": false,
          "legendFormat": "mean_job_consumption",
          "range": true,
          "refId": "B"
        }
      ],
      "title": "Mean Ideal Job Consumption",
      "transformations": [],
      "type": "stat"
    },
    {
      "datasource": {
        "type": "prometheus",
        "uid": "trixprometheus"
      },
      "fieldConfig": {
        "defaults": {
          "color": {
            "fixedColor": "#808080",
            "mode": "fixed"
          },
          "custom": {
            "axisCenteredZero": false,
            "axisColorMode": "text",
            "axisLabel": "",
            "axisPlacement": "auto",
            "barAlignment": 0,
            "drawStyle": "line",
            "fillOpacity": 10,
            "gradientMode": "none",
            "hideFrom": {
              "legend": false,
              "tooltip": false,
              "viz": false
            },
            "insertNulls": false,
            "lineInterpolation": "linear",
            "lineWidth": 1,
            "pointSize": 5,
            "scaleDistribution": {
              "type": "linear"
            },
            "showPoints": "auto",
            "spanNulls": false,
            "stacking": {
              "group": "A",
              "mode": "none"
            },
            "thresholdsStyle": {
              "mode": "off"
            }
          },
          "mappings": [],
          "min": 0,
          "thresholds": {
            "mode": "absolute",
            "steps": [
              {
                "color": "green",
                "value": null
              }
            ]
          },
          "unit": "watt"
        },
        "overrides": []
      },
      "gridPos": {
        "h": 4,
        "w": 21,
        "x": 3,
        "y": 18
      },
      "id": 40,
      "options": {
        "legend": {
          "calcs": [],
          "displayMode": "list",
          "placement": "bottom",
          "showLegend": false
        },
        "tooltip": {
          "mode": "single",
          "sort": "none"
        }
      },
      "pluginVersion": "10.1.2",
      "targets": [
        {
          "datasource": {
            "type": "prometheus",
            "uid": "trixprometheus"
          },
          "editorMode": "code",
          "expr": "sum(ipmi_dcmi_power_consumption_watts{hostname=~\"$hostname\"})\r\n*\r\nsum(rate(slurm_job_total_cpu_time{jobid=~\"$job_id\",hostname=~\"$hostname\"}[$__rate_interval:]))\r\n/\r\nsum(rate(node_cpu_seconds_total{hostname=~\"$hostname\"}[$__rate_interval:]))",
          "hide": false,
          "instant": false,
          "legendFormat": "__auto",
          "range": true,
          "refId": "B"
        }
      ],
      "title": "Ideal Job Consumption",
      "transformations": [],
      "type": "timeseries"
    },
    {
      "datasource": {
        "type": "prometheus",
        "uid": "trixprometheus"
      },
      "fieldConfig": {
        "defaults": {
          "color": {
            "fixedColor": "#808080",
            "mode": "continuous-GrYlRd"
          },
          "mappings": [
            {
              "options": {
                "match": "null+nan",
                "result": {
                  "color": "#808080",
                  "index": 0
                }
              },
              "type": "special"
            }
          ],
          "min": 0,
          "thresholds": {
            "mode": "absolute",
            "steps": [
              {
                "color": "green",
                "value": null
              }
            ]
          },
          "unit": "watt"
        },
        "overrides": []
      },
      "gridPos": {
        "h": 4,
        "w": 3,
        "x": 0,
        "y": 22
      },
      "id": 45,
      "options": {
        "colorMode": "value",
        "graphMode": "area",
        "justifyMode": "auto",
        "orientation": "auto",
        "reduceOptions": {
          "calcs": [
            "mean"
          ],
          "fields": "",
          "values": false
        },
        "textMode": "auto"
      },
      "pluginVersion": "10.1.2",
      "targets": [
        {
          "datasource": {
            "type": "prometheus",
            "uid": "trixprometheus"
          },
          "editorMode": "code",
          "expr": "sum(ipmi_dcmi_power_consumption_watts{hostname=~\"$hostname\"})\r\n*\r\n( sum(rate(slurm_job_total_cpu_time{jobid=~\"$job_id\", hostname=~\"$hostname\"}[$__rate_interval:])))\r\n/\r\n( sum(rate(slurm_job_total_cpu_time{hostname=~\"$hostname\"}[$__rate_interval:])) OR vector(1) )",
          "hide": false,
          "instant": false,
          "legendFormat": "amortized_mean_job_consumption",
          "range": true,
          "refId": "B"
        },
        {
          "datasource": {
            "type": "prometheus",
            "uid": "trixprometheus"
          },
          "editorMode": "code",
          "expr": "sum(ipmi_dcmi_power_consumption_watts{hostname=~\"$hostname\"})\r\n*\r\n( sum(rate(slurm_job_total_cpu_time{jobid=~\"$job_id\", hostname=~\"$hostname\"}[$__rate_interval:])) OR vector(0) )\r\n/\r\nsum(rate(node_cpu_seconds_total{hostname=~\"$hostname\"}[$__rate_interval:]))\r\nOR \r\nvector(0)",
          "hide": false,
          "instant": false,
          "legendFormat": "min_job_consumption",
          "range": true,
          "refId": "A"
        },
        {
          "datasource": {
            "type": "prometheus",
            "uid": "trixprometheus"
          },
          "editorMode": "code",
          "expr": "max(\r\n(\r\n    sum(ipmi_dcmi_power_consumption_watts{hostname=~\"$hostname\"}) * 4\r\n    *\r\n    sum(rate(slurm_job_total_cpu_time{jobid=~\"$job_id\", hostname=~\"$hostname\"}[$__rate_interval:]))\r\n    /\r\n    sum(rate(node_cpu_seconds_total{hostname=~\"$hostname\"}[$__rate_interval:]))\r\n) \r\nOR\r\n(\r\n    sum(ipmi_dcmi_power_consumption_watts{hostname=~\"$hostname\"})\r\n    *\r\n    ( sum(rate(slurm_job_total_cpu_time{jobid=~\"$job_id\", hostname=~\"$hostname\"}[$__rate_interval:])) )\r\n    /\r\n    ( sum(rate(slurm_job_total_cpu_time{jobid=~\"$job_id\", hostname=~\"$hostname\"}[$__rate_interval:])) OR vector(1) )\r\n\r\n)\r\n)",
          "hide": false,
          "instant": false,
          "legendFormat": "max_job_consumption",
          "range": true,
          "refId": "C"
        }
      ],
      "title": "Mean Actual Job Consumption",
      "transformations": [
        {
          "id": "configFromData",
          "options": {
            "configRefId": "A",
            "mappings": [
              {
                "fieldName": "min_job_consumption",
                "handlerKey": "min"
              }
            ]
          }
        },
        {
          "id": "configFromData",
          "options": {
            "configRefId": "C",
            "mappings": [
              {
                "fieldName": "max_job_consumption",
                "handlerKey": "max"
              }
            ]
          }
        }
      ],
      "type": "stat"
    },
    {
      "datasource": {
        "type": "prometheus",
        "uid": "trixprometheus"
      },
      "fieldConfig": {
        "defaults": {
          "color": {
            "mode": "continuous-GrYlRd"
          },
          "custom": {
            "axisCenteredZero": false,
            "axisColorMode": "text",
            "axisLabel": "",
            "axisPlacement": "auto",
            "barAlignment": 0,
            "drawStyle": "line",
            "fillOpacity": 10,
            "gradientMode": "scheme",
            "hideFrom": {
              "legend": false,
              "tooltip": false,
              "viz": false
            },
            "insertNulls": false,
            "lineInterpolation": "linear",
            "lineWidth": 1,
            "pointSize": 5,
            "scaleDistribution": {
              "type": "linear"
            },
            "showPoints": "auto",
            "spanNulls": false,
            "stacking": {
              "group": "A",
              "mode": "none"
            },
            "thresholdsStyle": {
              "mode": "off"
            }
          },
          "mappings": [],
          "min": 0,
          "thresholds": {
            "mode": "absolute",
            "steps": [
              {
                "color": "green",
                "value": null
              }
            ]
          },
          "unit": "watt"
        },
        "overrides": []
      },
      "gridPos": {
        "h": 4,
        "w": 21,
        "x": 3,
        "y": 22
      },
      "id": 46,
      "options": {
        "legend": {
          "calcs": [],
          "displayMode": "list",
          "placement": "bottom",
          "showLegend": false
        },
        "tooltip": {
          "mode": "single",
          "sort": "none"
        }
      },
      "pluginVersion": "10.1.2",
      "targets": [
        {
          "datasource": {
            "type": "prometheus",
            "uid": "trixprometheus"
          },
          "editorMode": "code",
          "expr": "sum(ipmi_dcmi_power_consumption_watts{hostname=~\"$hostname\"})\r\n*\r\n( sum(rate(slurm_job_total_cpu_time{jobid=~\"$job_id\", hostname=~\"$hostname\"}[$__rate_interval:])))\r\n/\r\n( sum(rate(slurm_job_total_cpu_time{hostname=~\"$hostname\"}[$__rate_interval:])) OR vector(1) )",
          "hide": false,
          "instant": false,
          "legendFormat": "amortized_job_consumption",
          "range": true,
          "refId": "B"
        },
        {
          "datasource": {
            "type": "prometheus",
            "uid": "trixprometheus"
          },
          "editorMode": "code",
          "expr": "sum(ipmi_dcmi_power_consumption_watts{hostname=~\"$hostname\"})\r\n*\r\n( sum(rate(slurm_job_total_cpu_time{jobid=~\"$job_id\", hostname=~\"$hostname\"}[$__rate_interval:])) OR vector(0) )\r\n/\r\nsum(rate(node_cpu_seconds_total{hostname=~\"$hostname\"}[$__rate_interval:]))",
          "hide": false,
          "instant": false,
          "legendFormat": "min_job_consumption",
          "range": true,
          "refId": "A"
        },
        {
          "datasource": {
            "type": "prometheus",
            "uid": "trixprometheus"
          },
          "editorMode": "code",
          "expr": "max(\r\n(\r\n    sum(ipmi_dcmi_power_consumption_watts{hostname=~\"$hostname\"}) * 4\r\n    *\r\n    sum(rate(slurm_job_total_cpu_time{jobid=~\"$job_id\", hostname=~\"$hostname\"}[$__rate_interval:]))\r\n    /\r\n    sum(rate(node_cpu_seconds_total{hostname=~\"$hostname\"}[$__rate_interval:]))\r\n) \r\nOR\r\n(\r\n    sum(ipmi_dcmi_power_consumption_watts{hostname=~\"$hostname\"})\r\n    *\r\n    ( sum(rate(slurm_job_total_cpu_time{jobid=~\"$job_id\", hostname=~\"$hostname\"}[$__rate_interval:])) )\r\n    /\r\n    ( sum(rate(slurm_job_total_cpu_time{jobid=~\"$job_id\", hostname=~\"$hostname\"}[$__rate_interval:])) OR vector(1) )\r\n\r\n)\r\n)",
          "hide": false,
          "instant": false,
          "legendFormat": "max_job_consumption_1",
          "range": true,
          "refId": "C"
        }
      ],
      "title": "Actual Job Consumption",
      "transformations": [
        {
          "id": "configFromData",
          "options": {
            "configRefId": "A",
            "mappings": [
              {
                "fieldName": "min_job_consumption",
                "handlerKey": "min"
              }
            ]
          }
        },
        {
          "id": "configFromData",
          "options": {
            "applyTo": {
              "id": "byType",
              "options": "number"
            },
            "configRefId": "C",
            "mappings": [
              {
                "fieldName": "max_job_consumption_1",
                "handlerKey": "max"
              }
            ]
          }
        }
      ],
      "type": "timeseries"
    },
    {
      "datasource": {
        "type": "prometheus",
        "uid": "trixprometheus"
      },
      "description": "",
      "fieldConfig": {
        "defaults": {
          "color": {
            "mode": "palette-classic"
          },
          "custom": {
            "axisCenteredZero": false,
            "axisColorMode": "text",
            "axisLabel": "",
            "axisPlacement": "auto",
            "axisSoftMin": 0,
            "barAlignment": 0,
            "drawStyle": "line",
            "fillOpacity": 10,
            "gradientMode": "none",
            "hideFrom": {
              "legend": false,
              "tooltip": false,
              "viz": false
            },
            "insertNulls": false,
            "lineInterpolation": "linear",
            "lineStyle": {
              "fill": "solid"
            },
            "lineWidth": 1,
            "pointSize": 2,
            "scaleDistribution": {
              "type": "linear"
            },
            "showPoints": "never",
            "spanNulls": false,
            "stacking": {
              "group": "A",
              "mode": "normal"
            },
            "thresholdsStyle": {
              "mode": "off"
            }
          },
          "mappings": [],
          "thresholds": {
            "mode": "absolute",
            "steps": [
              {
                "color": "green",
                "value": null
              },
              {
                "color": "red",
                "value": 80
              }
            ]
          }
        },
        "overrides": [
          {
            "matcher": {
              "id": "byName",
              "options": "slurm_user_job"
            },
            "properties": [
              {
                "id": "color",
                "value": {
                  "fixedColor": "#56A64B",
                  "mode": "fixed"
                }
              }
            ]
          },
          {
            "matcher": {
              "id": "byName",
              "options": "slurm_system_job"
            },
            "properties": [
              {
                "id": "color",
                "value": {
                  "fixedColor": "#F2CC0C",
                  "mode": "fixed"
                }
              }
            ]
          }
        ]
      },
      "gridPos": {
        "h": 8,
        "w": 24,
        "x": 0,
        "y": 26
      },
      "id": 31,
      "options": {
        "legend": {
          "calcs": [
            "mean"
          ],
          "displayMode": "table",
          "placement": "right",
          "showLegend": true
        },
        "tooltip": {
          "mode": "multi",
          "sort": "none"
        }
      },
      "targets": [
        {
          "datasource": {
            "type": "prometheus",
            "uid": "trixprometheus"
          },
          "editorMode": "code",
          "expr": "sum(rate(slurm_job_user_cpu_time{jobid=~\"$job_id\",hostname=~\"$hostname\"}[$__rate_interval:])) ",
          "hide": false,
          "instant": false,
          "interval": "",
          "legendFormat": "slurm_user_job",
          "range": true,
          "refId": "B"
        },
        {
          "datasource": {
            "type": "prometheus",
            "uid": "trixprometheus"
          },
          "editorMode": "code",
          "expr": "sum(rate(slurm_job_system_cpu_time{jobid=~\"$job_id\",hostname=~\"$hostname\"}[$__rate_interval:]))",
          "hide": false,
          "instant": false,
          "interval": "",
          "legendFormat": "slurm_system_job",
          "range": true,
          "refId": "D"
        }
      ],
      "title": "Job CPU Load",
      "transformations": [],
      "type": "timeseries"
    },
    {
      "datasource": {
        "type": "prometheus",
        "uid": "trixprometheus"
      },
      "fieldConfig": {
        "defaults": {
          "color": {
            "mode": "palette-classic"
          },
          "custom": {
            "axisCenteredZero": false,
            "axisColorMode": "text",
            "axisLabel": "",
            "axisPlacement": "auto",
            "barAlignment": 0,
            "drawStyle": "line",
            "fillOpacity": 10,
            "gradientMode": "none",
            "hideFrom": {
              "legend": false,
              "tooltip": false,
              "viz": false
            },
            "insertNulls": false,
            "lineInterpolation": "linear",
            "lineWidth": 1,
            "pointSize": 5,
            "scaleDistribution": {
              "type": "linear"
            },
            "showPoints": "never",
            "spanNulls": false,
            "stacking": {
              "group": "A",
              "mode": "none"
            },
            "thresholdsStyle": {
              "mode": "off"
            }
          },
          "mappings": [],
          "thresholds": {
            "mode": "absolute",
            "steps": [
              {
                "color": "green",
                "value": null
              },
              {
                "color": "red",
                "value": 80
              }
            ]
          },
          "unit": "bytes"
        },
        "overrides": [
          {
            "matcher": {
              "id": "byRegexp",
              "options": "/virtual_memory/"
            },
            "properties": [
              {
                "id": "custom.stacking",
                "value": {
                  "group": "A",
                  "mode": "normal"
                }
              },
              {
                "id": "custom.fillOpacity",
                "value": 1
              },
              {
                "id": "color",
                "value": {
                  "fixedColor": "text",
                  "mode": "fixed"
                }
              }
            ]
          },
          {
            "matcher": {
              "id": "byRegexp",
              "options": "/resident_memory/"
            },
            "properties": [
              {
                "id": "custom.stacking",
                "value": {
                  "group": "B",
                  "mode": "normal"
                }
              },
              {
                "id": "color",
                "value": {
                  "fixedColor": "green",
                  "mode": "fixed"
                }
              }
            ]
          }
        ]
      },
      "gridPos": {
        "h": 7,
        "w": 24,
        "x": 0,
        "y": 34
      },
      "id": 2,
      "options": {
        "legend": {
          "calcs": [
            "mean"
          ],
          "displayMode": "table",
          "placement": "right",
          "showLegend": true
        },
        "tooltip": {
          "mode": "multi",
          "sort": "none"
        }
      },
      "targets": [
        {
          "datasource": {
            "type": "prometheus",
            "uid": "trixprometheus"
          },
          "editorMode": "code",
          "expr": "sum(slurm_job_virtual_memory_bytes{jobid=~\"${job_id}\"})",
          "instant": false,
          "legendFormat": "virtual_memory",
          "range": true,
          "refId": "A"
        },
        {
          "datasource": {
            "type": "prometheus",
            "uid": "trixprometheus"
          },
          "editorMode": "code",
          "expr": "sum(slurm_job_resident_memory_bytes{jobid=~\"${job_id}\"})",
          "hide": false,
          "instant": false,
          "legendFormat": "resident_memory",
          "range": true,
          "refId": "B"
        }
      ],
      "title": "Job Memory Usage",
      "type": "timeseries"
    },
    {
      "datasource": {
        "type": "prometheus",
        "uid": "trixprometheus"
      },
      "fieldConfig": {
        "defaults": {
          "color": {
            "mode": "palette-classic"
          },
          "custom": {
            "axisCenteredZero": true,
            "axisColorMode": "text",
            "axisLabel": "",
            "axisPlacement": "auto",
            "barAlignment": 0,
            "drawStyle": "line",
            "fillOpacity": 10,
            "gradientMode": "none",
            "hideFrom": {
              "legend": false,
              "tooltip": false,
              "viz": false
            },
            "insertNulls": false,
            "lineInterpolation": "linear",
            "lineWidth": 1,
            "pointSize": 5,
            "scaleDistribution": {
              "type": "linear"
            },
            "showPoints": "never",
            "spanNulls": false,
            "stacking": {
              "group": "A",
              "mode": "normal"
            },
            "thresholdsStyle": {
              "mode": "off"
            }
          },
          "mappings": [],
          "thresholds": {
            "mode": "absolute",
            "steps": [
              {
                "color": "green",
                "value": null
              },
              {
                "color": "red",
                "value": 80
              }
            ]
          },
          "unit": "rps"
        },
        "overrides": [
          {
            "matcher": {
              "id": "byName",
              "options": "writes"
            },
            "properties": [
              {
                "id": "color",
                "value": {
                  "fixedColor": "purple",
                  "mode": "fixed"
                }
              },
              {
                "id": "custom.transform",
                "value": "negative-Y"
              }
            ]
          },
          {
            "matcher": {
              "id": "byName",
              "options": "reads"
            },
            "properties": [
              {
                "id": "color",
                "value": {
                  "fixedColor": "green",
                  "mode": "fixed"
                }
              }
            ]
          }
        ]
      },
      "gridPos": {
        "h": 7,
        "w": 12,
        "x": 0,
        "y": 41
      },
      "id": 3,
      "options": {
        "legend": {
          "calcs": [
            "mean"
          ],
          "displayMode": "table",
          "placement": "right",
          "showLegend": true
        },
        "tooltip": {
          "mode": "multi",
          "sort": "none"
        }
      },
      "targets": [
        {
          "datasource": {
            "type": "prometheus",
            "uid": "trixprometheus"
          },
          "editorMode": "code",
          "expr": "sum(rate(slurm_job_reads{jobid=~\"$job_id\"}[$__rate_interval:]))",
          "instant": false,
          "legendFormat": "reads",
          "range": true,
          "refId": "A"
        },
        {
          "datasource": {
            "type": "prometheus",
            "uid": "trixprometheus"
          },
          "editorMode": "code",
          "expr": "sum(rate(slurm_job_writes{jobid=~\"$job_id\"}[$__rate_interval:]))",
          "hide": false,
          "instant": false,
          "legendFormat": "writes",
          "range": true,
          "refId": "B"
        }
      ],
      "title": "Job Reads / Writes",
      "type": "timeseries"
    },
    {
      "datasource": {
        "type": "prometheus",
        "uid": "trixprometheus"
      },
      "fieldConfig": {
        "defaults": {
          "color": {
            "mode": "palette-classic"
          },
          "custom": {
            "axisCenteredZero": true,
            "axisColorMode": "text",
            "axisLabel": "",
            "axisPlacement": "auto",
            "barAlignment": 0,
            "drawStyle": "line",
            "fillOpacity": 10,
            "gradientMode": "none",
            "hideFrom": {
              "legend": false,
              "tooltip": false,
              "viz": false
            },
            "insertNulls": false,
            "lineInterpolation": "linear",
            "lineWidth": 1,
            "pointSize": 5,
            "scaleDistribution": {
              "type": "linear"
            },
            "showPoints": "auto",
            "spanNulls": false,
            "stacking": {
              "group": "A",
              "mode": "none"
            },
            "thresholdsStyle": {
              "mode": "off"
            }
          },
          "mappings": [],
          "thresholds": {
            "mode": "absolute",
            "steps": [
              {
                "color": "green",
                "value": null
              },
              {
                "color": "red",
                "value": 80
              }
            ]
          },
          "unit": "binBps"
        },
        "overrides": [
          {
            "matcher": {
              "id": "byName",
              "options": "bytes_written"
            },
            "properties": [
              {
                "id": "color",
                "value": {
                  "fixedColor": "purple",
                  "mode": "fixed"
                }
              },
              {
                "id": "custom.transform",
                "value": "negative-Y"
              }
            ]
          }
        ]
      },
      "gridPos": {
        "h": 7,
        "w": 12,
        "x": 12,
        "y": 41
      },
      "id": 4,
      "options": {
        "legend": {
          "calcs": [
            "lastNotNull"
          ],
          "displayMode": "table",
          "placement": "right",
          "showLegend": true
        },
        "tooltip": {
          "mode": "multi",
          "sort": "none"
        }
      },
      "targets": [
        {
          "datasource": {
            "type": "prometheus",
            "uid": "trixprometheus"
          },
          "editorMode": "code",
          "expr": "sum(rate(slurm_job_read_bytes{jobid=~\"$job_id\"}[$__rate_interval:]))",
          "instant": false,
          "legendFormat": "bytes_read",
          "range": true,
          "refId": "A"
        },
        {
          "datasource": {
            "type": "prometheus",
            "uid": "trixprometheus"
          },
          "editorMode": "code",
          "expr": "sum(rate(slurm_job_write_bytes{jobid=~\"$job_id\"}[$__rate_interval:]))",
          "hide": false,
          "instant": false,
          "legendFormat": "bytes_written",
          "range": true,
          "refId": "B"
        },
        {
          "datasource": {
            "type": "prometheus",
            "uid": "trixprometheus"
          },
          "editorMode": "code",
          "expr": "sum(rate(slurm_job_cancelled_write_bytes{jobid=~\"$job_id\"}[$__rate_interval:]))",
          "hide": false,
          "instant": false,
          "legendFormat": "bytes_write_fail",
          "range": true,
          "refId": "C"
        }
      ],
      "title": "Job Reads / Writes (Bytes)",
      "type": "timeseries"
    }
  ],
  "refresh": "",
  "schemaVersion": 38,
  "style": "dark",
  "tags": [
    "dashboard",
    "slurm",
    "system"
  ],
  "templating": {
    "list": [
      {
        "current": {
          "selected": true,
          "text": [
            "All"
          ],
          "value": [
            "$__all"
          ]
        },
        "datasource": {
          "type": "prometheus",
          "uid": "trixprometheus"
        },
        "definition": "label_values(node_exporter_build_info,hostname)",
        "hide": 0,
        "includeAll": true,
        "label": "Machine ID",
        "multi": true,
        "name": "hostname",
        "options": [],
        "query": {
          "query": "label_values(node_exporter_build_info,hostname)",
          "refId": "PrometheusVariableQueryEditor-VariableQuery"
        },
        "refresh": 1,
        "regex": "",
        "skipUrlSync": false,
        "sort": 0,
        "type": "query"
      },
      {
        "current": {
          "selected": true,
          "text": [
            "All"
          ],
          "value": [
            "$__all"
          ]
        },
        "datasource": {
          "type": "prometheus",
          "uid": "trixprometheus"
        },
        "definition": "label_values(slurm_job_user_cpu_time,jobid)",
        "description": "Job ID",
        "hide": 0,
        "includeAll": true,
        "label": "Job ID",
        "multi": true,
        "name": "job_id",
        "options": [],
        "query": {
          "query": "label_values(slurm_job_user_cpu_time,jobid)",
          "refId": "PrometheusVariableQueryEditor-VariableQuery"
        },
        "refresh": 2,
        "regex": "",
        "skipUrlSync": false,
        "sort": 4,
        "type": "query"
      },
      {
        "current": {
          "selected": false,
          "text": "{} 0 1731583793000",
          "value": "{} 0 1731583793000"
        },
        "datasource": {
          "type": "prometheus",
          "uid": "trixprometheus"
        },
        "definition": "query_result((\t( sum(rate(slurm_job_system_cpu_time{hostname=~\"$hostname\"}[1m:]) OR vector(0) ))\t+\t( sum(rate(slurm_job_user_cpu_time{hostname=~\"$hostname\"}[1m:]) OR vector(0) )))/(\tsum(rate(node_cpu_seconds_total{hostname=~\"$hostname\"}[1m:]))))",
        "hide": 2,
        "includeAll": false,
        "multi": false,
        "name": "query0",
        "options": [],
        "query": {
          "query": "query_result((\t( sum(rate(slurm_job_system_cpu_time{hostname=~\"$hostname\"}[1m:]) OR vector(0) ))\t+\t( sum(rate(slurm_job_user_cpu_time{hostname=~\"$hostname\"}[1m:]) OR vector(0) )))/(\tsum(rate(node_cpu_seconds_total{hostname=~\"$hostname\"}[1m:]))))",
          "refId": "PrometheusVariableQueryEditor-VariableQuery"
        },
        "refresh": 1,
        "regex": "",
        "skipUrlSync": false,
        "sort": 0,
        "type": "query"
      }
    ]
  },
  "time": {
    "from": "now-1h",
    "to": "now"
  },
  "timepicker": {},
  "timezone": "",
  "title": "Slurm Jobs",
  "uid": "dfe8e0f3-30ae-4c5c-b4e3-17cdf8e09fa5",
  "version": 5,
  "weekStart": ""
}